Metadata-Version: 1.0
Name: stxldriver
Version: 0.1
Summary: HTTP Driver for SBIG STXL Cameras
Home-page: http://github.com/dkirkby/STXLDriver
Author: David Kirkby
Author-email: dkirkby@uci.edu
License: MIT
Platform: UNKNOWN
